plusportals/__init__.py
plusportals/client.py
plusportals/credentials.py
plusportals/info.py
plusportals/session.py
plusportals/tracker.py
plusportals-0.2.5.dist-info/LICENSE
plusportals-0.2.5.dist-info/METADATA
plusportals-0.2.5.dist-info/WHEEL
plusportals-0.2.5.dist-info/top_level.txt
plusportals-0.2.5.dist-info/RECORD
