Metadata-Version: 2.1
Name: plusportals
Version: 0.2.5
Summary: A reverse engineered API PlusPortals
Home-page: https://github.com/DhruvBisla/PlusPortalsAPI
Author: Dhruv Bisla
Author-email: bisladhruv@gmail.com
License: MIT
Keywords: api,reverse-engineered,plusportals,plusportalsapi
Platform: UNKNOWN
Classifier: Intended Audience :: Developers
Classifier: Programming Language :: Python :: 3
Classifier: License :: OSI Approved :: MIT License
Classifier: Operating System :: OS Independent
Requires: requests
Requires: lxml
Requires-Python: >=3.6
Requires-Dist: requests
Requires-Dist: lxml
